<customrecordtype scriptid="customrecord_nsa_emlplugin_map">
  <accesstype>CUSTRECORDENTRYPERM</accesstype>
  <allowattachments>F</allowattachments>
  <allowinlinedeleting>F</allowinlinedeleting>
  <allowinlinedetaching>T</allowinlinedetaching>
  <allowinlineediting>F</allowinlineediting>
  <allowmobileaccess>T</allowmobileaccess>
  <allownumberingoverride>F</allownumberingoverride>
  <allowquickadd>T</allowquickadd>
  <allowquicksearch>F</allowquicksearch>
  <allowuiaccess>T</allowuiaccess>
  <description>This custom record defined the parameters for CSV import mapping used by Email Capture Plugin Import Integrator</description>
  <enabledle>T</enabledle>
  <enablekeywords>T</enablekeywords>
  <enablemailmerge>F</enablemailmerge>
  <enablenametranslation>F</enablenametranslation>
  <enablenumbering>F</enablenumbering>
  <enableoptimisticlocking>T</enableoptimisticlocking>
  <enablesystemnotes>T</enablesystemnotes>
  <hierarchical>F</hierarchical>
  <icon></icon>
  <iconbuiltin>T</iconbuiltin>
  <iconindex></iconindex>
  <includeinsearchmenu>T</includeinsearchmenu>
  <includename>F</includename>
  <isinactive>F</isinactive>
  <isordered>F</isordered>
  <numberinginit></numberinginit>
  <numberingmindigits></numberingmindigits>
  <numberingprefix></numberingprefix>
  <numberingsuffix></numberingsuffix>
  <recordname>NSA : Email Capture Import Mapping</recordname>
  <showcreationdate>F</showcreationdate>
  <showcreationdateonlist>F</showcreationdateonlist>
  <showid>F</showid>
  <showlastmodified>F</showlastmodified>
  <showlastmodifiedonlist>F</showlastmodifiedonlist>
  <shownotes>T</shownotes>
  <showowner>F</showowner>
  <showownerallowchange>F</showownerallowchange>
  <showowneronlist>F</showowneronlist>
  <customrecordcustomfields>
    <customrecordcustomfield scriptid="custrecord_email_subj_keys">
      <accesslevel>2</accesslevel>
      <allowquickadd>F</allowquickadd>
      <applyformatting>F</applyformatting>
      <checkspelling>F</checkspelling>
      <defaultchecked>F</defaultchecked>
      <defaultselection></defaultselection>
      <defaultvalue></defaultvalue>
      <description></description>
      <displayheight></displayheight>
      <displaytype>NORMAL</displaytype>
      <displaywidth></displaywidth>
      <dynamicdefault></dynamicdefault>
      <encryptatrest>F</encryptatrest>
      <fieldtype>TEXT</fieldtype>
      <globalsearch>F</globalsearch>
      <help></help>
      <isformula>F</isformula>
      <ismandatory>F</ismandatory>
      <isparent>F</isparent>
      <label>Email Subject</label>
      <linktext></linktext>
      <maxlength></maxlength>
      <maxvalue></maxvalue>
      <minvalue></minvalue>
      <onparentdelete></onparentdelete>
      <parentsubtab></parentsubtab>
      <rolerestrict>F</rolerestrict>
      <searchcomparefield></searchcomparefield>
      <searchdefault></searchdefault>
      <searchlevel>2</searchlevel>
      <selectrecordtype></selectrecordtype>
      <showinlist>T</showinlist>
      <sourcefilterby></sourcefilterby>
      <sourcefrom></sourcefrom>
      <sourcelist></sourcelist>
      <storevalue>T</storevalue>
      <subtab></subtab>
    </customrecordcustomfield>
    <customrecordcustomfield scriptid="custrecord_sender_email">
      <accesslevel>2</accesslevel>
      <allowquickadd>F</allowquickadd>
      <applyformatting>F</applyformatting>
      <checkspelling>F</checkspelling>
      <defaultchecked>F</defaultchecked>
      <defaultselection></defaultselection>
      <defaultvalue></defaultvalue>
      <description></description>
      <displayheight></displayheight>
      <displaytype>NORMAL</displaytype>
      <displaywidth></displaywidth>
      <dynamicdefault></dynamicdefault>
      <encryptatrest>F</encryptatrest>
      <fieldtype>TEXT</fieldtype>
      <globalsearch>F</globalsearch>
      <help></help>
      <isformula>F</isformula>
      <ismandatory>F</ismandatory>
      <isparent>F</isparent>
      <label>Sender Email</label>
      <linktext></linktext>
      <maxlength></maxlength>
      <maxvalue></maxvalue>
      <minvalue></minvalue>
      <onparentdelete></onparentdelete>
      <parentsubtab></parentsubtab>
      <rolerestrict>F</rolerestrict>
      <searchcomparefield></searchcomparefield>
      <searchdefault></searchdefault>
      <searchlevel>2</searchlevel>
      <selectrecordtype></selectrecordtype>
      <showinlist>T</showinlist>
      <sourcefilterby></sourcefilterby>
      <sourcefrom></sourcefrom>
      <sourcelist></sourcelist>
      <storevalue>T</storevalue>
      <subtab></subtab>
    </customrecordcustomfield>
    <customrecordcustomfield scriptid="custrecord_email_mess_param">
      <accesslevel>2</accesslevel>
      <allowquickadd>F</allowquickadd>
      <applyformatting>F</applyformatting>
      <checkspelling>F</checkspelling>
      <defaultchecked>F</defaultchecked>
      <defaultselection></defaultselection>
      <defaultvalue></defaultvalue>
      <description></description>
      <displayheight></displayheight>
      <displaytype>NORMAL</displaytype>
      <displaywidth></displaywidth>
      <dynamicdefault></dynamicdefault>
      <encryptatrest>F</encryptatrest>
      <fieldtype>TEXT</fieldtype>
      <globalsearch>F</globalsearch>
      <help></help>
      <isformula>F</isformula>
      <ismandatory>F</ismandatory>
      <isparent>F</isparent>
      <label>Email Body Keywords</label>
      <linktext></linktext>
      <maxlength></maxlength>
      <maxvalue></maxvalue>
      <minvalue></minvalue>
      <onparentdelete></onparentdelete>
      <parentsubtab></parentsubtab>
      <rolerestrict>F</rolerestrict>
      <searchcomparefield></searchcomparefield>
      <searchdefault></searchdefault>
      <searchlevel>2</searchlevel>
      <selectrecordtype></selectrecordtype>
      <showinlist>T</showinlist>
      <sourcefilterby></sourcefilterby>
      <sourcefrom></sourcefrom>
      <sourcelist></sourcelist>
      <storevalue>T</storevalue>
      <subtab></subtab>
    </customrecordcustomfield>
    <customrecordcustomfield scriptid="custrecord_import_id">
      <accesslevel>2</accesslevel>
      <allowquickadd>F</allowquickadd>
      <applyformatting>F</applyformatting>
      <checkspelling>F</checkspelling>
      <defaultchecked>F</defaultchecked>
      <defaultselection></defaultselection>
      <defaultvalue></defaultvalue>
      <description></description>
      <displayheight></displayheight>
      <displaytype>NORMAL</displaytype>
      <displaywidth></displaywidth>
      <dynamicdefault></dynamicdefault>
      <encryptatrest>F</encryptatrest>
      <fieldtype>TEXT</fieldtype>
      <globalsearch>F</globalsearch>
      <help></help>
      <isformula>F</isformula>
      <ismandatory>F</ismandatory>
      <isparent>F</isparent>
      <label>CSV Import ID</label>
      <linktext></linktext>
      <maxlength></maxlength>
      <maxvalue></maxvalue>
      <minvalue></minvalue>
      <onparentdelete></onparentdelete>
      <parentsubtab></parentsubtab>
      <rolerestrict>F</rolerestrict>
      <searchcomparefield></searchcomparefield>
      <searchdefault></searchdefault>
      <searchlevel>2</searchlevel>
      <selectrecordtype></selectrecordtype>
      <showinlist>T</showinlist>
      <sourcefilterby></sourcefilterby>
      <sourcefrom></sourcefrom>
      <sourcelist></sourcelist>
      <storevalue>T</storevalue>
      <subtab></subtab>
    </customrecordcustomfield>
    <customrecordcustomfield scriptid="custrecord_upload_folder">
      <accesslevel>2</accesslevel>
      <allowquickadd>F</allowquickadd>
      <applyformatting>F</applyformatting>
      <checkspelling>F</checkspelling>
      <defaultchecked>F</defaultchecked>
      <defaultselection></defaultselection>
      <defaultvalue></defaultvalue>
      <description></description>
      <displayheight></displayheight>
      <displaytype>NORMAL</displaytype>
      <displaywidth></displaywidth>
      <dynamicdefault></dynamicdefault>
      <encryptatrest>F</encryptatrest>
      <fieldtype>TEXT</fieldtype>
      <globalsearch>F</globalsearch>
      <help></help>
      <isformula>F</isformula>
      <ismandatory>F</ismandatory>
      <isparent>F</isparent>
      <label>Upload Folder ID</label>
      <linktext></linktext>
      <maxlength></maxlength>
      <maxvalue></maxvalue>
      <minvalue></minvalue>
      <onparentdelete></onparentdelete>
      <parentsubtab></parentsubtab>
      <rolerestrict>F</rolerestrict>
      <searchcomparefield></searchcomparefield>
      <searchdefault></searchdefault>
      <searchlevel>2</searchlevel>
      <selectrecordtype></selectrecordtype>
      <showinlist>T</showinlist>
      <sourcefilterby></sourcefilterby>
      <sourcefrom></sourcefrom>
      <sourcelist></sourcelist>
      <storevalue>T</storevalue>
      <subtab></subtab>
    </customrecordcustomfield>
    <customrecordcustomfield scriptid="custrecord_error_report_author">
      <accesslevel>2</accesslevel>
      <allowquickadd>F</allowquickadd>
      <applyformatting>F</applyformatting>
      <checkspelling>F</checkspelling>
      <defaultchecked>F</defaultchecked>
      <defaultselection></defaultselection>
      <defaultvalue></defaultvalue>
      <description></description>
      <displayheight></displayheight>
      <displaytype>NORMAL</displaytype>
      <displaywidth></displaywidth>
      <dynamicdefault></dynamicdefault>
      <encryptatrest>F</encryptatrest>
      <fieldtype>SELECT</fieldtype>
      <globalsearch>F</globalsearch>
      <help></help>
      <isformula>F</isformula>
      <ismandatory>F</ismandatory>
      <isparent>F</isparent>
      <label>Error Report Sender</label>
      <linktext></linktext>
      <maxlength></maxlength>
      <maxvalue></maxvalue>
      <minvalue></minvalue>
      <onparentdelete>SET_NULL</onparentdelete>
      <parentsubtab></parentsubtab>
      <rolerestrict>F</rolerestrict>
      <searchcomparefield></searchcomparefield>
      <searchdefault></searchdefault>
      <searchlevel>2</searchlevel>
      <selectrecordtype>-4</selectrecordtype>
      <showinlist>T</showinlist>
      <sourcefilterby></sourcefilterby>
      <sourcefrom></sourcefrom>
      <sourcelist></sourcelist>
      <storevalue>T</storevalue>
      <subtab></subtab>
    </customrecordcustomfield>
    <customrecordcustomfield scriptid="custrecord_error_report_recipient">
      <accesslevel>2</accesslevel>
      <allowquickadd>F</allowquickadd>
      <applyformatting>F</applyformatting>
      <checkspelling>F</checkspelling>
      <defaultchecked>F</defaultchecked>
      <defaultselection></defaultselection>
      <defaultvalue></defaultvalue>
      <description></description>
      <displayheight></displayheight>
      <displaytype>NORMAL</displaytype>
      <displaywidth></displaywidth>
      <dynamicdefault></dynamicdefault>
      <encryptatrest>F</encryptatrest>
      <fieldtype>SELECT</fieldtype>
      <globalsearch>F</globalsearch>
      <help></help>
      <isformula>F</isformula>
      <ismandatory>F</ismandatory>
      <isparent>F</isparent>
      <label>Error Report Recipient</label>
      <linktext></linktext>
      <maxlength></maxlength>
      <maxvalue></maxvalue>
      <minvalue></minvalue>
      <onparentdelete>SET_NULL</onparentdelete>
      <parentsubtab></parentsubtab>
      <rolerestrict>F</rolerestrict>
      <searchcomparefield></searchcomparefield>
      <searchdefault></searchdefault>
      <searchlevel>2</searchlevel>
      <selectrecordtype>-4</selectrecordtype>
      <showinlist>T</showinlist>
      <sourcefilterby></sourcefilterby>
      <sourcefrom></sourcefrom>
      <sourcelist></sourcelist>
      <storevalue>T</storevalue>
      <subtab></subtab>
    </customrecordcustomfield>
    <customrecordcustomfield scriptid="custrecord_import_suitelet_id">
      <accesslevel>2</accesslevel>
      <allowquickadd>F</allowquickadd>
      <applyformatting>F</applyformatting>
      <checkspelling>F</checkspelling>
      <defaultchecked>F</defaultchecked>
      <defaultselection></defaultselection>
      <defaultvalue></defaultvalue>
      <description></description>
      <displayheight></displayheight>
      <displaytype>NORMAL</displaytype>
      <displaywidth></displaywidth>
      <dynamicdefault></dynamicdefault>
      <encryptatrest>F</encryptatrest>
      <fieldtype>TEXT</fieldtype>
      <globalsearch>F</globalsearch>
      <help></help>
      <isformula>F</isformula>
      <ismandatory>F</ismandatory>
      <isparent>F</isparent>
      <label>After Import Script ID</label>
      <linktext></linktext>
      <maxlength></maxlength>
      <maxvalue></maxvalue>
      <minvalue></minvalue>
      <onparentdelete></onparentdelete>
      <parentsubtab></parentsubtab>
      <rolerestrict>F</rolerestrict>
      <searchcomparefield></searchcomparefield>
      <searchdefault></searchdefault>
      <searchlevel>2</searchlevel>
      <selectrecordtype></selectrecordtype>
      <showinlist>T</showinlist>
      <sourcefilterby></sourcefilterby>
      <sourcefrom></sourcefrom>
      <sourcelist></sourcelist>
      <storevalue>T</storevalue>
      <subtab></subtab>
    </customrecordcustomfield>
    <customrecordcustomfield scriptid="custrecord_import_scr_dep_id">
      <accesslevel>2</accesslevel>
      <allowquickadd>F</allowquickadd>
      <applyformatting>F</applyformatting>
      <checkspelling>F</checkspelling>
      <defaultchecked>F</defaultchecked>
      <defaultselection></defaultselection>
      <defaultvalue></defaultvalue>
      <description></description>
      <displayheight></displayheight>
      <displaytype>NORMAL</displaytype>
      <displaywidth></displaywidth>
      <dynamicdefault></dynamicdefault>
      <encryptatrest>F</encryptatrest>
      <fieldtype>TEXT</fieldtype>
      <globalsearch>F</globalsearch>
      <help></help>
      <isformula>F</isformula>
      <ismandatory>F</ismandatory>
      <isparent>F</isparent>
      <label>Script Deployment ID</label>
      <linktext></linktext>
      <maxlength></maxlength>
      <maxvalue></maxvalue>
      <minvalue></minvalue>
      <onparentdelete></onparentdelete>
      <parentsubtab></parentsubtab>
      <rolerestrict>F</rolerestrict>
      <searchcomparefield></searchcomparefield>
      <searchdefault></searchdefault>
      <searchlevel>2</searchlevel>
      <selectrecordtype></selectrecordtype>
      <showinlist>T</showinlist>
      <sourcefilterby></sourcefilterby>
      <sourcefrom></sourcefrom>
      <sourcelist></sourcelist>
      <storevalue>T</storevalue>
      <subtab></subtab>
    </customrecordcustomfield>
    <customrecordcustomfield scriptid="custrecord_is_testing">
      <accesslevel>2</accesslevel>
      <allowquickadd>F</allowquickadd>
      <applyformatting>F</applyformatting>
      <checkspelling>F</checkspelling>
      <defaultchecked>F</defaultchecked>
      <defaultselection></defaultselection>
      <defaultvalue></defaultvalue>
      <description></description>
      <displayheight></displayheight>
      <displaytype>NORMAL</displaytype>
      <displaywidth></displaywidth>
      <dynamicdefault></dynamicdefault>
      <encryptatrest>F</encryptatrest>
      <fieldtype>CHECKBOX</fieldtype>
      <globalsearch>F</globalsearch>
      <help></help>
      <isformula>F</isformula>
      <ismandatory>F</ismandatory>
      <isparent>F</isparent>
      <label>Testing</label>
      <linktext></linktext>
      <maxlength></maxlength>
      <maxvalue></maxvalue>
      <minvalue></minvalue>
      <onparentdelete></onparentdelete>
      <parentsubtab></parentsubtab>
      <rolerestrict>F</rolerestrict>
      <searchcomparefield></searchcomparefield>
      <searchdefault></searchdefault>
      <searchlevel>2</searchlevel>
      <selectrecordtype></selectrecordtype>
      <showinlist>T</showinlist>
      <sourcefilterby></sourcefilterby>
      <sourcefrom></sourcefrom>
      <sourcelist></sourcelist>
      <storevalue>T</storevalue>
      <subtab></subtab>
    </customrecordcustomfield>
    <customrecordcustomfield scriptid="custrecord_import_sndrecpt">
      <accesslevel>2</accesslevel>
      <allowquickadd>F</allowquickadd>
      <applyformatting>F</applyformatting>
      <checkspelling>F</checkspelling>
      <defaultchecked>F</defaultchecked>
      <defaultselection></defaultselection>
      <defaultvalue></defaultvalue>
      <description></description>
      <displayheight></displayheight>
      <displaytype>NORMAL</displaytype>
      <displaywidth></displaywidth>
      <dynamicdefault></dynamicdefault>
      <encryptatrest>F</encryptatrest>
      <fieldtype>CHECKBOX</fieldtype>
      <globalsearch>F</globalsearch>
      <help></help>
      <isformula>F</isformula>
      <ismandatory>F</ismandatory>
      <isparent>F</isparent>
      <label>Send Receipt Email</label>
      <linktext></linktext>
      <maxlength></maxlength>
      <maxvalue></maxvalue>
      <minvalue></minvalue>
      <onparentdelete></onparentdelete>
      <parentsubtab></parentsubtab>
      <rolerestrict>F</rolerestrict>
      <searchcomparefield></searchcomparefield>
      <searchdefault></searchdefault>
      <searchlevel>2</searchlevel>
      <selectrecordtype></selectrecordtype>
      <showinlist>T</showinlist>
      <sourcefilterby></sourcefilterby>
      <sourcefrom></sourcefrom>
      <sourcelist></sourcelist>
      <storevalue>T</storevalue>
      <subtab></subtab>
    </customrecordcustomfield>
  </customrecordcustomfields>
</customrecordtype>